{"page_current":1,"page_maximum":4582,"total":146618,"items":[{"id":75226289,"url":"https:\/\/bringatrailer.com\/listing\/1982-mercedes-benz-240d-60\/","title":"26k-Mile 1982 Mercedes-Benz 240D 4-Speed","subtitle":"Sold for $38,750  on 5\/11\/24 ","images":{"small":{"height":150,"width":150,"url":"https:\/\/bringatrailer.com\/wp-content\/uploads\/2024\/05\/1982_mercedes-benz_240d_IMG-14675-68147-scaled.jpg?resize=235%2C159"},"large":{"height":150,"width":150,"url":"https:\/\/bringatrailer.com\/wp-content\/uploads\/2024\/05\/1982_mercedes-benz_240d_IMG-14675-68147-scaled.jpg?resize=235%2C159"}}},{"id":74915253,"url":"https:\/\/bringatrailer.com\/listing\/1968-chevrolet-c10-pickup-126\/","title":"383-Powered 1968 Chevrolet C10 Pickup 4-Speed","subtitle":"Sold for $29,600  on 5\/11\/24 ","images":{"small":{"height":150,"width":150,"url":"https:\/\/bringatrailer.com\/wp-content\/uploads\/2024\/04\/1968_chevrolet_c10-pickup_1000000649-83741.jpg?resize=235%2C159"},"large":{"height":150,"width":150,"url":"https:\/\/bringatrailer.com\/wp-content\/uploads\/2024\/04\/1968_chevrolet_c10-pickup_1000000649-83741.jpg?resize=235%2C159"}}},{"id":74083944,"url":"https:\/\/bringatrailer.com\/listing\/2016-land-rover-range-rover-35\/","title":"25k-Mile 2016 Land Rover Range Rover HSE","subtitle":"Sold for $35,750  on 5\/11\/24 ","images":{"small":{"height":150,"width":150,"url":"https:\/\/bringatrailer.com\/wp-content\/uploads\/2024\/04\/2016_land-rover_range-rover_img_0261-01207.jpg?resize=235%2C159"},"large":{"height":150,"width":150,"url":"https:\/\/bringatrailer.com\/wp-content\/uploads\/2024\/04\/2016_land-rover_range-rover_img_0261-01207.jpg?resize=235%2C159"}}},{"id":73668310,"url":"https:\/\/bringatrailer.com\/listing\/2008-audi-a8l\/","title":"No Reserve: 2008 Audi A8L","subtitle":"Sold for $12,500  on 5\/11\/24 ","images":{"small":{"height":150,"width":150,"url":"https:\/\/bringatrailer.com\/wp-content\/uploads\/2024\/04\/2008_audi_a8l_img_8616-64514.jpeg?resize=235%2C159"},"large":{"height":150,"width":150,"url":"https:\/\/bringatrailer.com\/wp-content\/uploads\/2024\/04\/2008_audi_a8l_img_8616-64514.jpeg?resize=235%2C159"}}},{"id":74835691,"url":"https:\/\/bringatrailer.com\/listing\/1973-volkswagen-super-beetle-sedan-4\/","title":"No Reserve: 1973 Volkswagen Super Beetle Sedan","subtitle":"Sold for $9,250  on 5\/11\/24 ","images":{"small":{"height":150,"width":150,"url":"https:\/\/bringatrailer.com\/wp-content\/uploads\/2024\/04\/1973_volkswagen_super-beetle-sedan_1000005269-04077.jpg?resize=235%2C159"},"large":{"height":150,"width":150,"url":"https:\/\/bringatrailer.com\/wp-content\/uploads\/2024\/04\/1973_volkswagen_super-beetle-sedan_1000005269-04077.jpg?resize=235%2C159"}}},{"id":75167351,"url":"https:\/\/bringatrailer.com\/listing\/2001-mazda-mx-5-miata-ls-8\/","title":"No Reserve: 2001 Mazda MX-5 Miata LS 6-Speed","subtitle":"Sold for $11,000  on 5\/11\/24 ","images":{"small":{"height":150,"width":150,"url":"https:\/\/bringatrailer.com\/wp-content\/uploads\/2024\/05\/2001_mazda_mx-5-miata-ls_20240430_175821-84346.jpg?resize=235%2C159"},"large":{"height":150,"width":150,"url":"https:\/\/bringatrailer.com\/wp-content\/uploads\/2024\/05\/2001_mazda_mx-5-miata-ls_20240430_175821-84346.jpg?resize=235%2C159"}}},{"id":75052887,"url":"https:\/\/bringatrailer.com\/listing\/1987-jaguar-xj-s-v12-7\/","title":"No Reserve: 50k-Mile 1987 Jaguar XJ-S V12","subtitle":"Sold for $11,400  on 5\/11\/24 ","images":{"small":{"height":150,"width":150,"url":"https:\/\/bringatrailer.com\/wp-content\/uploads\/2024\/04\/1987_jaguar_xj-s-v12_img_3354-85995.jpeg?resize=235%2C159"},"large":{"height":150,"width":150,"url":"https:\/\/bringatrailer.com\/wp-content\/uploads\/2024\/04\/1987_jaguar_xj-s-v12_img_3354-85995.jpeg?resize=235%2C159"}}},{"id":74213448,"url":"https:\/\/bringatrailer.com\/listing\/testa-rossa-documents\/","title":"No Reserve: Ferrari 250 Testa Rossa Documents","subtitle":"Sold for $6,000  on 5\/11\/24 ","images":{"small":{"height":150,"width":150,"url":"https:\/\/bringatrailer.com\/wp-content\/uploads\/2024\/04\/1959_ferrari_250-testarossa_img_0007-83903.jpg?resize=235%2C159"},"large":{"height":150,"width":150,"url":"https:\/\/bringatrailer.com\/wp-content\/uploads\/2024\/04\/1959_ferrari_250-testarossa_img_0007-83903.jpg?resize=235%2C159"}}},{"id":75102207,"url":"https:\/\/bringatrailer.com\/listing\/1994-mercedes-benz-e320-wagon-8\/","title":"1994 Mercedes-Benz E320 Wagon","subtitle":"Sold for $11,950  on 5\/11\/24 ","images":{"small":{"height":150,"width":150,"url":"https:\/\/bringatrailer.com\/wp-content\/uploads\/2024\/04\/1994_mercedes-benz_e320-wagon_img_1254-96729.jpeg?resize=235%2C159"},"large":{"height":150,"width":150,"url":"https:\/\/bringatrailer.com\/wp-content\/uploads\/2024\/04\/1994_mercedes-benz_e320-wagon_img_1254-96729.jpeg?resize=235%2C159"}}},{"id":74682929,"url":"https:\/\/bringatrailer.com\/listing\/2004-porsche-911-turbo-cabriolet-154\/","title":"2004 Porsche 911 Turbo Cabriolet X50 6-Speed","subtitle":"Sold for $65,500  on 5\/11\/24 ","images":{"small":{"height":150,"width":150,"url":"https:\/\/bringatrailer.com\/wp-content\/uploads\/2024\/04\/2004_porsche_911-turbo-cabriolet_2004_porsche_911-turbo-cabriolet_d3577683-1a6e-44b8-bfd3-6ea856500f62-l70GTE-56600-56601-scaled.jpg?resize=235%2C159"},"large":{"height":150,"width":150,"url":"https:\/\/bringatrailer.com\/wp-content\/uploads\/2024\/04\/2004_porsche_911-turbo-cabriolet_2004_porsche_911-turbo-cabriolet_d3577683-1a6e-44b8-bfd3-6ea856500f62-l70GTE-56600-56601-scaled.jpg?resize=235%2C159"}}},{"id":59093977,"url":"https:\/\/bringatrailer.com\/listing\/no-reserve-1995-land-rover-range-rover-county-classic-swb-2\/","title":"No Reserve: 1995 Land Rover Range Rover County Classic SWB","subtitle":"Sold for $42,000  on 5\/11\/24 ","images":{"small":{"height":150,"width":150,"url":"https:\/\/bringatrailer.com\/wp-content\/uploads\/2023\/05\/1995_land-rover_range-rover-county-classic_20230804_172537-28925.jpg?resize=235%2C159"},"large":{"height":150,"width":150,"url":"https:\/\/bringatrailer.com\/wp-content\/uploads\/2023\/05\/1995_land-rover_range-rover-county-classic_20230804_172537-28925.jpg?resize=235%2C159"}}},{"id":74342476,"url":"https:\/\/bringatrailer.com\/listing\/2008-bentley-continental-gtc-35\/","title":"No Reserve: 2008 Bentley Continental GTC","subtitle":"Sold for $38,551  on 5\/11\/24 ","images":{"small":{"height":150,"width":150,"url":"https:\/\/bringatrailer.com\/wp-content\/uploads\/2024\/04\/2008_bentley_continental-gtc_img_0540-55472.jpg?resize=235%2C159"},"large":{"height":150,"width":150,"url":"https:\/\/bringatrailer.com\/wp-content\/uploads\/2024\/04\/2008_bentley_continental-gtc_img_0540-55472.jpg?resize=235%2C159"}}},{"id":73717877,"url":"https:\/\/bringatrailer.com\/listing\/2003-mercedes-benz-clk320-coupe-c209-5\/","title":"No Reserve: 18k-Mile 2003 Mercedes-Benz CLK320 Coupe","subtitle":"Sold for $8,900  on 5\/11\/24 ","images":{"small":{"height":150,"width":150,"url":"https:\/\/bringatrailer.com\/wp-content\/uploads\/2024\/04\/2003_mercedes-benz_clk320-coupe-c209_2003_mercedes-benz_clk320-coupe-c209_7cb2e920-24aa-425a-8cfb-197018c97344-wvqc2p-60525-85790.jpg?resize=235%2C159"},"large":{"height":150,"width":150,"url":"https:\/\/bringatrailer.com\/wp-content\/uploads\/2024\/04\/2003_mercedes-benz_clk320-coupe-c209_2003_mercedes-benz_clk320-coupe-c209_7cb2e920-24aa-425a-8cfb-197018c97344-wvqc2p-60525-85790.jpg?resize=235%2C159"}}},{"id":74507852,"url":"https:\/\/bringatrailer.com\/listing\/2015-jeep-wrangler-116\/","title":"No Reserve: 2015 Jeep Wrangler Sport","subtitle":"Sold for $10,300  on 5\/11\/24 ","images":{"small":{"height":150,"width":150,"url":"https:\/\/bringatrailer.com\/wp-content\/uploads\/2024\/04\/2015_jeep_wrangler_dsc_0177-28037.jpg?resize=235%2C159"},"large":{"height":150,"width":150,"url":"https:\/\/bringatrailer.com\/wp-content\/uploads\/2024\/04\/2015_jeep_wrangler_dsc_0177-28037.jpg?resize=235%2C159"}}},{"id":74261541,"url":"https:\/\/bringatrailer.com\/listing\/1973-chevrolet-corvette-coupe-28\/","title":"1973 Chevrolet Corvette Coupe 454 4-Speed","subtitle":"Sold for $18,250  on 5\/11\/24 ","images":{"small":{"height":150,"width":150,"url":"https:\/\/bringatrailer.com\/wp-content\/uploads\/2024\/04\/1973_chevrolet_corvette-coupe_img_0638-68832.jpeg?resize=235%2C159"},"large":{"height":150,"width":150,"url":"https:\/\/bringatrailer.com\/wp-content\/uploads\/2024\/04\/1973_chevrolet_corvette-coupe_img_0638-68832.jpeg?resize=235%2C159"}}},{"id":59679612,"url":"https:\/\/bringatrailer.com\/listing\/1965-chrysler-town-country-4\/","title":"No Reserve: 24-Years-Owned 1965 Chrysler New Yorker Town & Country Wagon","subtitle":"Sold for $10,465  on 5\/11\/24 ","images":{"small":{"height":150,"width":150,"url":"https:\/\/bringatrailer.com\/wp-content\/uploads\/2023\/05\/1965_chrysler_town-country_1965_chrysler_town-country_IMG_2-84927.jpeg?resize=235%2C159"},"large":{"height":150,"width":150,"url":"https:\/\/bringatrailer.com\/wp-content\/uploads\/2023\/05\/1965_chrysler_town-country_1965_chrysler_town-country_IMG_2-84927.jpeg?resize=235%2C159"}}},{"id":70864867,"url":"https:\/\/bringatrailer.com\/listing\/2006-mercedes-benz-cls55-amg-19\/","title":"27k-Mile 2006 Mercedes-Benz CLS55 AMG","subtitle":"Sold for $25,750  on 5\/11\/24 ","images":{"small":{"height":150,"width":150,"url":"https:\/\/bringatrailer.com\/wp-content\/uploads\/2024\/01\/2006_mercedes-benz_cls55-amg_n5a5458-60512.jpg?resize=235%2C159"},"large":{"height":150,"width":150,"url":"https:\/\/bringatrailer.com\/wp-content\/uploads\/2024\/01\/2006_mercedes-benz_cls55-amg_n5a5458-60512.jpg?resize=235%2C159"}}},{"id":74899134,"url":"https:\/\/bringatrailer.com\/listing\/2009-porsche-cayenne-turbo-s-45\/","title":"No Reserve: 2009 Porsche Cayenne Turbo S","subtitle":"Sold for $18,000  on 5\/11\/24 ","images":{"small":{"height":150,"width":150,"url":"https:\/\/bringatrailer.com\/wp-content\/uploads\/2024\/04\/2009_porsche_cayenne-turbo-s_img_2240-20198.jpeg?resize=235%2C159"},"large":{"height":150,"width":150,"url":"https:\/\/bringatrailer.com\/wp-content\/uploads\/2024\/04\/2009_porsche_cayenne-turbo-s_img_2240-20198.jpeg?resize=235%2C159"}}},{"id":74711107,"url":"https:\/\/bringatrailer.com\/listing\/1997-toyota-4runner-100\/","title":"No Reserve: 1997 Toyota 4Runner 5-Speed","subtitle":"Sold for $8,600  on 5\/11\/24 ","images":{"small":{"height":150,"width":150,"url":"https:\/\/bringatrailer.com\/wp-content\/uploads\/2024\/04\/1997_toyota_4runner_bbe00252-2188-4d69-a1cb-347ccfd74c73-78616.jpeg?resize=235%2C159"},"large":{"height":150,"width":150,"url":"https:\/\/bringatrailer.com\/wp-content\/uploads\/2024\/04\/1997_toyota_4runner_bbe00252-2188-4d69-a1cb-347ccfd74c73-78616.jpeg?resize=235%2C159"}}},{"id":74430523,"url":"https:\/\/bringatrailer.com\/listing\/1969-ford-bronco-205\/","title":"Modified 1969 Ford Bronco 302","subtitle":"Sold for $72,005  on 5\/11\/24 ","images":{"small":{"height":150,"width":150,"url":"https:\/\/bringatrailer.com\/wp-content\/uploads\/2024\/04\/1969_ford_bronco_fullsizerender-167-23550.jpg?resize=235%2C159"},"large":{"height":150,"width":150,"url":"https:\/\/bringatrailer.com\/wp-content\/uploads\/2024\/04\/1969_ford_bronco_fullsizerender-167-23550.jpg?resize=235%2C159"}}},{"id":75184746,"url":"https:\/\/bringatrailer.com\/listing\/neon-sign-15\/","title":"No Reserve: Neon Shell Sign","subtitle":"Sold for $5,100  on 5\/11\/24 ","images":{"small":{"height":150,"width":150,"url":"https:\/\/bringatrailer.com\/wp-content\/uploads\/2024\/05\/1000025972-66503.jpg?resize=235%2C159"},"large":{"height":150,"width":150,"url":"https:\/\/bringatrailer.com\/wp-content\/uploads\/2024\/05\/1000025972-66503.jpg?resize=235%2C159"}}},{"id":74684106,"url":"https:\/\/bringatrailer.com\/listing\/2008-mercedes-benz-s600-19\/","title":"2008 Mercedes-Benz S600","subtitle":"Sold for $20,500  on 5\/11\/24 ","images":{"small":{"height":150,"width":150,"url":"https:\/\/bringatrailer.com\/wp-content\/uploads\/2024\/04\/2008_mercedes-benz_s600_img_2853-74538.jpeg?resize=235%2C159"},"large":{"height":150,"width":150,"url":"https:\/\/bringatrailer.com\/wp-content\/uploads\/2024\/04\/2008_mercedes-benz_s600_img_2853-74538.jpeg?resize=235%2C159"}}},{"id":74639605,"url":"https:\/\/bringatrailer.com\/listing\/1999-porsche-911-carrera-cabriolet-87-2\/","title":"No Reserve: 1999 Porsche 911 Carrera Cabriolet","subtitle":"Sold for $23,001  on 5\/11\/24 ","images":{"small":{"height":150,"width":150,"url":"https:\/\/bringatrailer.com\/wp-content\/uploads\/2024\/04\/1999_porsche_911-carrera-cabriolet_p1009860-11145.jpg?resize=235%2C159"},"large":{"height":150,"width":150,"url":"https:\/\/bringatrailer.com\/wp-content\/uploads\/2024\/04\/1999_porsche_911-carrera-cabriolet_p1009860-11145.jpg?resize=235%2C159"}}},{"id":73086088,"url":"https:\/\/bringatrailer.com\/listing\/2004-dodge-viper-srt-10-roadster-31\/","title":"13k-Kilometer 2004 Dodge Viper SRT-10 Roadster","subtitle":"Sold for $61,388  on 5\/11\/24 ","images":{"small":{"height":150,"width":150,"url":"https:\/\/bringatrailer.com\/wp-content\/uploads\/2024\/03\/2004_dodge_viper-srt-10-roadster_2004_dodge_viper-srt-10-roadster_0ddad062-af31-4a63-9f47-b9b425527206-otkbnr-46674-97701.jpg?resize=235%2C159"},"large":{"height":150,"width":150,"url":"https:\/\/bringatrailer.com\/wp-content\/uploads\/2024\/03\/2004_dodge_viper-srt-10-roadster_2004_dodge_viper-srt-10-roadster_0ddad062-af31-4a63-9f47-b9b425527206-otkbnr-46674-97701.jpg?resize=235%2C159"}}},{"id":74421036,"url":"https:\/\/bringatrailer.com\/listing\/2006-jeep-wrangler-220\/","title":"2006 Jeep Wrangler Unlimited Rubicon 6-Speed","subtitle":"Bid to $15,757  on 5\/11\/24 ","images":{"small":{"height":150,"width":150,"url":"https:\/\/bringatrailer.com\/wp-content\/uploads\/2024\/04\/2006_jeep_wrangler_2006-jeep-wrangler-unlimited-rubicon-1j4fa64s56p741177_6029-55480.jpeg?resize=235%2C159"},"large":{"height":150,"width":150,"url":"https:\/\/bringatrailer.com\/wp-content\/uploads\/2024\/04\/2006_jeep_wrangler_2006-jeep-wrangler-unlimited-rubicon-1j4fa64s56p741177_6029-55480.jpeg?resize=235%2C159"}}},{"id":74693686,"url":"https:\/\/bringatrailer.com\/listing\/2001-bmw-k1200rs-4\/","title":"No Reserve: 2001 BMW K1200RS","subtitle":"Sold for $3,750  on 5\/11\/24 ","images":{"small":{"height":150,"width":150,"url":"https:\/\/bringatrailer.com\/wp-content\/uploads\/2024\/04\/2001_bmw_k1200rs_20240410_084446-76497.jpg?resize=235%2C159"},"large":{"height":150,"width":150,"url":"https:\/\/bringatrailer.com\/wp-content\/uploads\/2024\/04\/2001_bmw_k1200rs_20240410_084446-76497.jpg?resize=235%2C159"}}},{"id":74394194,"url":"https:\/\/bringatrailer.com\/listing\/2006-bmw-m3-convertible-105\/","title":"49k-Mile 2006 BMW M3 Convertible","subtitle":"Bid to $18,000  on 5\/11\/24 ","images":{"small":{"height":150,"width":150,"url":"https:\/\/bringatrailer.com\/wp-content\/uploads\/2024\/04\/2006_bmw_m3-convertible_img_0224-11930.jpeg?resize=235%2C159"},"large":{"height":150,"width":150,"url":"https:\/\/bringatrailer.com\/wp-content\/uploads\/2024\/04\/2006_bmw_m3-convertible_img_0224-11930.jpeg?resize=235%2C159"}}},{"id":74608783,"url":"https:\/\/bringatrailer.com\/listing\/2023-mclaren-artura-2\/","title":"2023 McLaren Artura","subtitle":"Bid to $166,000  on 5\/11\/24 ","images":{"small":{"height":150,"width":150,"url":"https:\/\/bringatrailer.com\/wp-content\/uploads\/2024\/04\/2023_mclaren_artura_dsc_1179-new-78006.png?resize=235%2C159"},"large":{"height":150,"width":150,"url":"https:\/\/bringatrailer.com\/wp-content\/uploads\/2024\/04\/2023_mclaren_artura_dsc_1179-new-78006.png?resize=235%2C159"}}},{"id":74471596,"url":"https:\/\/bringatrailer.com\/listing\/2017-mercedes-amg-g63-17\/","title":"No Reserve: 2017 Mercedes-AMG G63","subtitle":"Sold for $100,000  on 5\/11\/24 ","images":{"small":{"height":150,"width":150,"url":"https:\/\/bringatrailer.com\/wp-content\/uploads\/2024\/04\/2017_mercedes-amg_g63_img_5144-24826.jpeg?resize=235%2C159"},"large":{"height":150,"width":150,"url":"https:\/\/bringatrailer.com\/wp-content\/uploads\/2024\/04\/2017_mercedes-amg_g63_img_5144-24826.jpeg?resize=235%2C159"}}},{"id":74816284,"url":"https:\/\/bringatrailer.com\/listing\/pontiac-400-engine\/","title":"No Reserve: Pontiac 400 Engine","subtitle":"Sold for $13,000  on 5\/11\/24 ","images":{"small":{"height":150,"width":150,"url":"https:\/\/bringatrailer.com\/wp-content\/uploads\/2024\/04\/img_20240424_104145523_hdr-18225.jpg?resize=235%2C159"},"large":{"height":150,"width":150,"url":"https:\/\/bringatrailer.com\/wp-content\/uploads\/2024\/04\/img_20240424_104145523_hdr-18225.jpg?resize=235%2C159"}}},{"id":74463369,"url":"https:\/\/bringatrailer.com\/listing\/2012-land-rover-range-rover-sport-35\/","title":"No Reserve: 2012 Land Rover Range Rover Sport HSE Luxury","subtitle":"Sold for $15,250  on 5\/11\/24 ","images":{"small":{"height":150,"width":150,"url":"https:\/\/bringatrailer.com\/wp-content\/uploads\/2024\/04\/2012_land-rover_range-rover-sport_pics4cars.com-34-17909.jpg?resize=235%2C159"},"large":{"height":150,"width":150,"url":"https:\/\/bringatrailer.com\/wp-content\/uploads\/2024\/04\/2012_land-rover_range-rover-sport_pics4cars.com-34-17909.jpg?resize=235%2C159"}}},{"id":74278431,"url":"https:\/\/bringatrailer.com\/listing\/1977-porsche-930-turbo-6\/","title":"Japanese-Market 1977 Porsche 930 Turbo 3.0","subtitle":"Sold for $152,000  on 5\/11\/24 ","images":{"small":{"height":150,"width":150,"url":"https:\/\/bringatrailer.com\/wp-content\/uploads\/2024\/04\/1977_porsche_turbo-carrera-3.0_pics4cars.com-137-39579.jpg?resize=235%2C159"},"large":{"height":150,"width":150,"url":"https:\/\/bringatrailer.com\/wp-content\/uploads\/2024\/04\/1977_porsche_turbo-carrera-3.0_pics4cars.com-137-39579.jpg?resize=235%2C159"}}}]}