{"page_current":1,"page_maximum":2218,"total":70965,"items":[{"id":41391915,"url":"https:\/\/bringatrailer.com\/listing\/1995-mercedes-benz-sl500-40\/","title":"1995 Mercedes-Benz SL500","subtitle":"Bid to $9,400 on 4\/17\/22","images":{"small":{"height":150,"width":150,"url":"https:\/\/bringatrailer.com\/wp-content\/uploads\/2022\/03\/IMG_5892-9.29.27-PM-18332.jpg?resize=235%2C159"},"large":{"height":150,"width":150,"url":"https:\/\/bringatrailer.com\/wp-content\/uploads\/2022\/03\/IMG_5892-9.29.27-PM-18332.jpg?resize=235%2C159"}}},{"id":40585151,"url":"https:\/\/bringatrailer.com\/listing\/1991-mercedes-benz-560sel-33\/","title":"38k-Mile 1991 Mercedes-Benz 560SEL","subtitle":"Sold for $38,750 on 4\/17\/22","images":{"small":{"height":150,"width":150,"url":"https:\/\/bringatrailer.com\/wp-content\/uploads\/2022\/03\/1991_mercedes-benz_560sel_028-3-93146.jpg?resize=235%2C159"},"large":{"height":150,"width":150,"url":"https:\/\/bringatrailer.com\/wp-content\/uploads\/2022\/03\/1991_mercedes-benz_560sel_028-3-93146.jpg?resize=235%2C159"}}},{"id":40310632,"url":"https:\/\/bringatrailer.com\/listing\/1993-chevrolet-suburban-2500-silverado-3\/","title":"No Reserve: 1993 Chevrolet Suburban K2500 Silverado 4x4","subtitle":"Sold for $34,000 on 4\/17\/22","images":{"small":{"height":150,"width":150,"url":"https:\/\/bringatrailer.com\/wp-content\/uploads\/2022\/03\/1993_chevrolet_suburban-2500-silverado_1993_chevrolet_suburban-2500-silverado_180d77b5-c38a-4f76-86ba-63015a3506ce-m7idhk-82116-63243.jpg?resize=235%2C159"},"large":{"height":150,"width":150,"url":"https:\/\/bringatrailer.com\/wp-content\/uploads\/2022\/03\/1993_chevrolet_suburban-2500-silverado_1993_chevrolet_suburban-2500-silverado_180d77b5-c38a-4f76-86ba-63015a3506ce-m7idhk-82116-63243.jpg?resize=235%2C159"}}},{"id":39527989,"url":"https:\/\/bringatrailer.com\/listing\/2006-jaguar-super-v8-2\/","title":"No Reserve: 36k-Mile 2006 Jaguar Super V8","subtitle":"Sold for $27,500 on 4\/17\/22","images":{"small":{"height":150,"width":150,"url":"https:\/\/bringatrailer.com\/wp-content\/uploads\/2022\/02\/2006_jaguar_super-v8_img_0935-79516.jpeg?resize=235%2C159"},"large":{"height":150,"width":150,"url":"https:\/\/bringatrailer.com\/wp-content\/uploads\/2022\/02\/2006_jaguar_super-v8_img_0935-79516.jpeg?resize=235%2C159"}}},{"id":39232659,"url":"https:\/\/bringatrailer.com\/listing\/1963-chevrolet-corvette-142\/","title":"1963 Chevrolet Corvette Split-Window Coupe 327\/360 Fuelie 4-Speed","subtitle":"Sold for $325,000 on 4\/17\/22","images":{"small":{"height":150,"width":150,"url":"https:\/\/bringatrailer.com\/wp-content\/uploads\/2022\/02\/1963_chevrolet_corvette_Doug-QF007-89086-scaled.jpg?resize=235%2C159"},"large":{"height":150,"width":150,"url":"https:\/\/bringatrailer.com\/wp-content\/uploads\/2022\/02\/1963_chevrolet_corvette_Doug-QF007-89086-scaled.jpg?resize=235%2C159"}}},{"id":41437517,"url":"https:\/\/bringatrailer.com\/listing\/2002-porsche-911-carrera-4s-62\/","title":"2002 Porsche 911 Carrera 4S Coupe 6-Speed","subtitle":"Sold for $40,250 on 4\/17\/22","images":{"small":{"height":150,"width":150,"url":"https:\/\/bringatrailer.com\/wp-content\/uploads\/2022\/03\/2002_porsche_911-carrera-4s_2002_porsche_911-carrera-4s_761602dc-fa22-4d2f-a79b-5fbed8442efa-xhivs9-08755-78823.jpg?resize=235%2C159"},"large":{"height":150,"width":150,"url":"https:\/\/bringatrailer.com\/wp-content\/uploads\/2022\/03\/2002_porsche_911-carrera-4s_2002_porsche_911-carrera-4s_761602dc-fa22-4d2f-a79b-5fbed8442efa-xhivs9-08755-78823.jpg?resize=235%2C159"}}},{"id":40717095,"url":"https:\/\/bringatrailer.com\/listing\/1972-chevrolet-k10-4x4-pickup-20\/","title":"1972 Chevrolet K10 4x4","subtitle":"Sold for $26,750 on 4\/17\/22","images":{"small":{"height":150,"width":150,"url":"https:\/\/bringatrailer.com\/wp-content\/uploads\/2022\/03\/1972_chevrolet_k10-4x4-pickup_1972_chevrolet_k10-4x4-pickup_77826966-f840-47ee-981a-f9bc8e970b0a-j8xtdn-58976-73681.jpg?resize=235%2C159"},"large":{"height":150,"width":150,"url":"https:\/\/bringatrailer.com\/wp-content\/uploads\/2022\/03\/1972_chevrolet_k10-4x4-pickup_1972_chevrolet_k10-4x4-pickup_77826966-f840-47ee-981a-f9bc8e970b0a-j8xtdn-58976-73681.jpg?resize=235%2C159"}}},{"id":41044444,"url":"https:\/\/bringatrailer.com\/listing\/2005-porsche-cayenne-s-6\/","title":"No Reserve: 2005 Porsche Cayenne S","subtitle":"Sold for $11,750 on 4\/17\/22","images":{"small":{"height":150,"width":150,"url":"https:\/\/bringatrailer.com\/wp-content\/uploads\/2022\/03\/2005_porsche_cayenne-s_dsc_0101-17-57610.jpg?resize=235%2C159"},"large":{"height":150,"width":150,"url":"https:\/\/bringatrailer.com\/wp-content\/uploads\/2022\/03\/2005_porsche_cayenne-s_dsc_0101-17-57610.jpg?resize=235%2C159"}}},{"id":40783510,"url":"https:\/\/bringatrailer.com\/listing\/2003-bmw-m3-coupe-165\/","title":"Modified 34k-Mile 2003 BMW M3 Coupe 6-Speed","subtitle":"Bid to $45,250 on 4\/17\/22","images":{"small":{"height":150,"width":150,"url":"https:\/\/bringatrailer.com\/wp-content\/uploads\/2022\/03\/2003_bmw_m3-coupe_2003_bmw_m3-coupe_75e97a7a-692a-4940-91f7-2e175d68e8cc-xj6idw-13948-13038.jpg?resize=235%2C159"},"large":{"height":150,"width":150,"url":"https:\/\/bringatrailer.com\/wp-content\/uploads\/2022\/03\/2003_bmw_m3-coupe_2003_bmw_m3-coupe_75e97a7a-692a-4940-91f7-2e175d68e8cc-xj6idw-13948-13038.jpg?resize=235%2C159"}}},{"id":40312740,"url":"https:\/\/bringatrailer.com\/listing\/2000-jeep-cherokee-62\/","title":"No Reserve: 2000 Jeep Cherokee Sport 4x4","subtitle":"Sold for $9,250 on 4\/17\/22","images":{"small":{"height":150,"width":150,"url":"https:\/\/bringatrailer.com\/wp-content\/uploads\/2022\/03\/2000_jeep_cherokee_tempimagehaa1n4-74629.jpg?resize=235%2C159"},"large":{"height":150,"width":150,"url":"https:\/\/bringatrailer.com\/wp-content\/uploads\/2022\/03\/2000_jeep_cherokee_tempimagehaa1n4-74629.jpg?resize=235%2C159"}}},{"id":40771699,"url":"https:\/\/bringatrailer.com\/listing\/1974-ford-bronco-101\/","title":"1974 Ford Bronco Ranger","subtitle":"Sold for $81,000 on 4\/17\/22","images":{"small":{"height":150,"width":150,"url":"https:\/\/bringatrailer.com\/wp-content\/uploads\/2022\/03\/1974_ford_bronco_1974_ford_bronco_1d67b702-bc33-4428-8c8d-3a63506d1ac8-n3bijz-44496-65531.jpg?resize=235%2C159"},"large":{"height":150,"width":150,"url":"https:\/\/bringatrailer.com\/wp-content\/uploads\/2022\/03\/1974_ford_bronco_1974_ford_bronco_1d67b702-bc33-4428-8c8d-3a63506d1ac8-n3bijz-44496-65531.jpg?resize=235%2C159"}}},{"id":40685485,"url":"https:\/\/bringatrailer.com\/listing\/2004-mercedes-benz-sl600-68\/","title":"2004 Mercedes-Benz SL600","subtitle":"Sold for $13,800 on 4\/17\/22","images":{"small":{"height":150,"width":150,"url":"https:\/\/bringatrailer.com\/wp-content\/uploads\/2022\/03\/2004_mercedes-benz_sl600_2004_mercedes-benz_sl600_5dc44874-d5de-4a50-9444-faf2780691db-shgC5A-97072-97073-scaled.jpg?resize=235%2C159"},"large":{"height":150,"width":150,"url":"https:\/\/bringatrailer.com\/wp-content\/uploads\/2022\/03\/2004_mercedes-benz_sl600_2004_mercedes-benz_sl600_5dc44874-d5de-4a50-9444-faf2780691db-shgC5A-97072-97073-scaled.jpg?resize=235%2C159"}}},{"id":39837161,"url":"https:\/\/bringatrailer.com\/listing\/1970-toyota-land-cruiser-fj40-45\/","title":"350-Powered 1970 Toyota Land Cruiser FJ40 5-Speed","subtitle":"Sold for $69,500 on 4\/17\/22","images":{"small":{"height":150,"width":150,"url":"https:\/\/bringatrailer.com\/wp-content\/uploads\/2022\/02\/1970_toyota_land-cruiser-fj40_1970_toyota_land-cruiser-fj40_e90cd623-5ae0-4f1a-9b52-3a935aa5486c-w0mhh7-25796-93819.jpg?resize=235%2C159"},"large":{"height":150,"width":150,"url":"https:\/\/bringatrailer.com\/wp-content\/uploads\/2022\/02\/1970_toyota_land-cruiser-fj40_1970_toyota_land-cruiser-fj40_e90cd623-5ae0-4f1a-9b52-3a935aa5486c-w0mhh7-25796-93819.jpg?resize=235%2C159"}}},{"id":40781135,"url":"https:\/\/bringatrailer.com\/listing\/1958-chevrolet-corvette-44\/","title":"LS-Powered 1958 Chevrolet Corvette 6-Speed","subtitle":"Bid to $117,000 on 4\/17\/22","images":{"small":{"height":150,"width":150,"url":"https:\/\/bringatrailer.com\/wp-content\/uploads\/2022\/03\/1958_chevrolet_corvette_1958_chevrolet_corvette_10963177-6ede-47f0-a1a7-1d872f85806c-42n2dx-90645-43907.jpg?resize=235%2C159"},"large":{"height":150,"width":150,"url":"https:\/\/bringatrailer.com\/wp-content\/uploads\/2022\/03\/1958_chevrolet_corvette_1958_chevrolet_corvette_10963177-6ede-47f0-a1a7-1d872f85806c-42n2dx-90645-43907.jpg?resize=235%2C159"}}},{"id":41447869,"url":"https:\/\/bringatrailer.com\/listing\/1988-toyota-4runner-v6-4x4-33\/","title":"No Reserve: 1988 Toyota 4Runner SR5 V6 4x4 5-Speed","subtitle":"Sold for $31,000 on 4\/17\/22","images":{"small":{"height":150,"width":150,"url":"https:\/\/bringatrailer.com\/wp-content\/uploads\/2022\/03\/1988_toyota_4runner-v6-4x4_116_0149-87311.jpg?resize=235%2C159"},"large":{"height":150,"width":150,"url":"https:\/\/bringatrailer.com\/wp-content\/uploads\/2022\/03\/1988_toyota_4runner-v6-4x4_116_0149-87311.jpg?resize=235%2C159"}}},{"id":41350630,"url":"https:\/\/bringatrailer.com\/listing\/1997-bmw-m3-249\/","title":"LS1-Powered 1997 BMW M3 Sedan 6-Speed","subtitle":"Sold for $20,000 on 4\/17\/22","images":{"small":{"height":150,"width":150,"url":"https:\/\/bringatrailer.com\/wp-content\/uploads\/2022\/03\/1997_bmw_m3_dsc_0716-1-58210.jpg?resize=235%2C159"},"large":{"height":150,"width":150,"url":"https:\/\/bringatrailer.com\/wp-content\/uploads\/2022\/03\/1997_bmw_m3_dsc_0716-1-58210.jpg?resize=235%2C159"}}},{"id":40948081,"url":"https:\/\/bringatrailer.com\/listing\/1989-bmw-325is-78\/","title":"1989 BMW 325is 5-Speed","subtitle":"Sold for $25,750 on 4\/17\/22","images":{"small":{"height":150,"width":150,"url":"https:\/\/bringatrailer.com\/wp-content\/uploads\/2022\/03\/1989_bmw_325is_dscf2596-1-14205.jpg?resize=235%2C159"},"large":{"height":150,"width":150,"url":"https:\/\/bringatrailer.com\/wp-content\/uploads\/2022\/03\/1989_bmw_325is_dscf2596-1-14205.jpg?resize=235%2C159"}}},{"id":41277281,"url":"https:\/\/bringatrailer.com\/listing\/1994-porsche-968-35\/","title":"1994 Porsche 968 Coupe 6-Speed","subtitle":"Bid to $32,000 on 4\/17\/22","images":{"small":{"height":150,"width":150,"url":"https:\/\/bringatrailer.com\/wp-content\/uploads\/2022\/03\/1994_porsche_968_1-41-99881.jpg?resize=235%2C159"},"large":{"height":150,"width":150,"url":"https:\/\/bringatrailer.com\/wp-content\/uploads\/2022\/03\/1994_porsche_968_1-41-99881.jpg?resize=235%2C159"}}},{"id":40750520,"url":"https:\/\/bringatrailer.com\/listing\/1997-ford-f-250-100\/","title":"1997 Ford F-250 HD XLT Power Stroke 4\u00d74","subtitle":"Sold for $38,997 on 4\/17\/22","images":{"small":{"height":150,"width":150,"url":"https:\/\/bringatrailer.com\/wp-content\/uploads\/2022\/03\/1997_ford_f-250_1997_ford_f-250_6eddac73-e4ec-4b68-91ae-361df0c8e519-apVgrp-07403-07404-scaled.jpg?resize=235%2C159"},"large":{"height":150,"width":150,"url":"https:\/\/bringatrailer.com\/wp-content\/uploads\/2022\/03\/1997_ford_f-250_1997_ford_f-250_6eddac73-e4ec-4b68-91ae-361df0c8e519-apVgrp-07403-07404-scaled.jpg?resize=235%2C159"}}},{"id":38389072,"url":"https:\/\/bringatrailer.com\/listing\/1965-mercedes-benz-230sl-35\/","title":"1965 Mercedes-Benz 230SL 4-Speed","subtitle":"Bid to $52,501 on 4\/17\/22","images":{"small":{"height":150,"width":150,"url":"https:\/\/bringatrailer.com\/wp-content\/uploads\/2022\/01\/1965_mercedes-benz_230sl_1965_mercedes-benz_230sl_2a98662a-ca44-4898-a576-2feb1f1484cc-3qUo6g-34846-34847-scaled.jpg?resize=235%2C159"},"large":{"height":150,"width":150,"url":"https:\/\/bringatrailer.com\/wp-content\/uploads\/2022\/01\/1965_mercedes-benz_230sl_1965_mercedes-benz_230sl_2a98662a-ca44-4898-a576-2feb1f1484cc-3qUo6g-34846-34847-scaled.jpg?resize=235%2C159"}}},{"id":40687941,"url":"https:\/\/bringatrailer.com\/listing\/1956-cadillac-sixty-special-3\/","title":"1956 Cadillac Fleetwood Sixty Special","subtitle":"Sold for $31,000 on 4\/17\/22","images":{"small":{"height":150,"width":150,"url":"https:\/\/bringatrailer.com\/wp-content\/uploads\/2022\/03\/1956_cadillac_sixty-special_p1140083-1-45986.jpg?resize=235%2C159"},"large":{"height":150,"width":150,"url":"https:\/\/bringatrailer.com\/wp-content\/uploads\/2022\/03\/1956_cadillac_sixty-special_p1140083-1-45986.jpg?resize=235%2C159"}}},{"id":40827400,"url":"https:\/\/bringatrailer.com\/listing\/1973-chevrolet-corvette-43\/","title":"1973 Chevrolet Corvette Coupe","subtitle":"Sold for $25,250 on 4\/17\/22","images":{"small":{"height":150,"width":150,"url":"https:\/\/bringatrailer.com\/wp-content\/uploads\/2022\/03\/1973_chevrolet_corvette_002a-33381.jpeg?resize=235%2C159"},"large":{"height":150,"width":150,"url":"https:\/\/bringatrailer.com\/wp-content\/uploads\/2022\/03\/1973_chevrolet_corvette_002a-33381.jpeg?resize=235%2C159"}}},{"id":40851708,"url":"https:\/\/bringatrailer.com\/listing\/1993-mercedes-benz-190e-36\/","title":"No Reserve: 39k-Mile 1993 Mercedes-Benz 190E 2.3","subtitle":"Sold for $18,000 on 4\/17\/22","images":{"small":{"height":150,"width":150,"url":"https:\/\/bringatrailer.com\/wp-content\/uploads\/2022\/03\/1-11-15194-scaled.jpg?resize=235%2C159"},"large":{"height":150,"width":150,"url":"https:\/\/bringatrailer.com\/wp-content\/uploads\/2022\/03\/1-11-15194-scaled.jpg?resize=235%2C159"}}},{"id":23771984,"url":"https:\/\/bringatrailer.com\/listing\/1971-land-rover-land-rover-santana-88\/","title":"1971 Land Rover 88 Series IIA Santana","subtitle":"Sold for $37,000 on 4\/17\/22","images":{"small":{"height":150,"width":150,"url":"https:\/\/bringatrailer.com\/wp-content\/uploads\/2020\/12\/1971_land-rover_land-rover-santana-88_2f507a34-6c17-42ec-bacf-4e3ab8459189-61832.jpeg?resize=235%2C159"},"large":{"height":150,"width":150,"url":"https:\/\/bringatrailer.com\/wp-content\/uploads\/2020\/12\/1971_land-rover_land-rover-santana-88_2f507a34-6c17-42ec-bacf-4e3ab8459189-61832.jpeg?resize=235%2C159"}}},{"id":40748043,"url":"https:\/\/bringatrailer.com\/listing\/2016-chevrolet-corvette-z06-23\/","title":"589-Mile 2016 Chevrolet Corvette Z06 Coupe 2LZ Z07","subtitle":"Sold for $85,000 on 4\/17\/22","images":{"small":{"height":150,"width":150,"url":"https:\/\/bringatrailer.com\/wp-content\/uploads\/2022\/03\/2016_chevrolet_corvette-z06_2016_chevrolet_corvette-z06_004a4e07-e544-4570-898f-2fd72a558ecd-CHgjeu-11167-11168-scaled.jpg?resize=235%2C159"},"large":{"height":150,"width":150,"url":"https:\/\/bringatrailer.com\/wp-content\/uploads\/2022\/03\/2016_chevrolet_corvette-z06_2016_chevrolet_corvette-z06_004a4e07-e544-4570-898f-2fd72a558ecd-CHgjeu-11167-11168-scaled.jpg?resize=235%2C159"}}},{"id":40678676,"url":"https:\/\/bringatrailer.com\/listing\/1969-dodge-charger-32\/","title":"No Reserve: 1969 Dodge Charger Project","subtitle":"Sold for $45,000 on 4\/17\/22","images":{"small":{"height":150,"width":150,"url":"https:\/\/bringatrailer.com\/wp-content\/uploads\/2022\/03\/1969_dodge_charger_20220307_140904-51600.jpg?resize=235%2C159"},"large":{"height":150,"width":150,"url":"https:\/\/bringatrailer.com\/wp-content\/uploads\/2022\/03\/1969_dodge_charger_20220307_140904-51600.jpg?resize=235%2C159"}}},{"id":41103480,"url":"https:\/\/bringatrailer.com\/listing\/1978-datsun-280z-117-2\/","title":"1978 Datsun 280Z 5-Speed","subtitle":"Sold for $23,250 on 4\/17\/22","images":{"small":{"height":150,"width":150,"url":"https:\/\/bringatrailer.com\/wp-content\/uploads\/2022\/03\/1978_datsun_280z_4d37b117-230d-47e0-b7bc-61214b5377f8-92198.jpeg?resize=235%2C159"},"large":{"height":150,"width":150,"url":"https:\/\/bringatrailer.com\/wp-content\/uploads\/2022\/03\/1978_datsun_280z_4d37b117-230d-47e0-b7bc-61214b5377f8-92198.jpeg?resize=235%2C159"}}},{"id":40649282,"url":"https:\/\/bringatrailer.com\/listing\/2011-bmw-1m-101\/","title":"31k-Mile 2011 BMW 1M","subtitle":"Sold for $76,000 on 4\/17\/22","images":{"small":{"height":150,"width":150,"url":"https:\/\/bringatrailer.com\/wp-content\/uploads\/2022\/03\/2011_bmw_1m_2011_bmw_1m_ba4c39c4-ab26-43fb-819d-57ed8ea5dad5-aq3jeu-93101-44001.jpg?resize=235%2C159"},"large":{"height":150,"width":150,"url":"https:\/\/bringatrailer.com\/wp-content\/uploads\/2022\/03\/2011_bmw_1m_2011_bmw_1m_ba4c39c4-ab26-43fb-819d-57ed8ea5dad5-aq3jeu-93101-44001.jpg?resize=235%2C159"}}},{"id":40677278,"url":"https:\/\/bringatrailer.com\/listing\/1996-land-rover-defender-130-2\/","title":"No Reserve: 1996 Land Rover Defender 130","subtitle":"Sold for $83,000 on 4\/17\/22","images":{"small":{"height":150,"width":150,"url":"https:\/\/bringatrailer.com\/wp-content\/uploads\/2022\/03\/1996_land-rover_defender-130_img_1300-3-78348.jpg?resize=235%2C159"},"large":{"height":150,"width":150,"url":"https:\/\/bringatrailer.com\/wp-content\/uploads\/2022\/03\/1996_land-rover_defender-130_img_1300-3-78348.jpg?resize=235%2C159"}}},{"id":41057356,"url":"https:\/\/bringatrailer.com\/listing\/2009-aprilia-rs125-3\/","title":"No Reserve: Original-Owner 2009 Aprilia RS 125 Race Replica","subtitle":"Sold for $7,200 on 4\/17\/22","images":{"small":{"height":150,"width":150,"url":"https:\/\/bringatrailer.com\/wp-content\/uploads\/2022\/03\/2009_aprilia_rs125_32f56d77-f596-4895-8e30-daaa24ea014f-08738.jpeg?resize=235%2C159"},"large":{"height":150,"width":150,"url":"https:\/\/bringatrailer.com\/wp-content\/uploads\/2022\/03\/2009_aprilia_rs125_32f56d77-f596-4895-8e30-daaa24ea014f-08738.jpeg?resize=235%2C159"}}},{"id":40870608,"url":"https:\/\/bringatrailer.com\/listing\/2006-porsche-boxster-s-24\/","title":"14k-Mile 2006 Porsche Boxster S 6-Speed","subtitle":"Sold for $40,750 on 4\/17\/22","images":{"small":{"height":150,"width":150,"url":"https:\/\/bringatrailer.com\/wp-content\/uploads\/2022\/03\/2006_porsche_boxster-s_0cd6ddef-32ae-4066-8560-cadca3a7046c-49724.jpeg?resize=235%2C159"},"large":{"height":150,"width":150,"url":"https:\/\/bringatrailer.com\/wp-content\/uploads\/2022\/03\/2006_porsche_boxster-s_0cd6ddef-32ae-4066-8560-cadca3a7046c-49724.jpeg?resize=235%2C159"}}},{"id":40681744,"url":"https:\/\/bringatrailer.com\/listing\/1987-mercedes-benz-560sl-293\/","title":"Single-Family-Owned 1987 Mercedes-Benz 560SL","subtitle":"Sold for $28,000 on 4\/17\/22","images":{"small":{"height":150,"width":150,"url":"https:\/\/bringatrailer.com\/wp-content\/uploads\/2022\/03\/1987_mercedes-benz_560sl_1987_mercedes-benz_560sl_a59d2f82-b04b-49c0-9293-f1d74ada6a2e-ANfvE5-73291-73292-scaled.jpg?resize=235%2C159"},"large":{"height":150,"width":150,"url":"https:\/\/bringatrailer.com\/wp-content\/uploads\/2022\/03\/1987_mercedes-benz_560sl_1987_mercedes-benz_560sl_a59d2f82-b04b-49c0-9293-f1d74ada6a2e-ANfvE5-73291-73292-scaled.jpg?resize=235%2C159"}}}]}