{"page_current":1,"page_maximum":4462,"total":142780,"items":[{"id":73236965,"url":"https:\/\/bringatrailer.com\/listing\/1964-ford-galaxie-500-83\/","title":"No Reserve: 456-Powered 1964 Ford Galaxie 500 Convertible 4-Speed","subtitle":"Sold for $39,250  on 4\/9\/24 ","images":{"small":{"height":150,"width":150,"url":"https:\/\/bringatrailer.com\/wp-content\/uploads\/2024\/03\/1964_ford_galaxie-500_img_5395-25545.jpg?resize=235%2C159"},"large":{"height":150,"width":150,"url":"https:\/\/bringatrailer.com\/wp-content\/uploads\/2024\/03\/1964_ford_galaxie-500_img_5395-25545.jpg?resize=235%2C159"}}},{"id":73325877,"url":"https:\/\/bringatrailer.com\/listing\/1969-mg-mgc-roadster-4\/","title":"1969 MG MGC Roadster","subtitle":"Sold for $29,000  on 4\/9\/24 ","images":{"small":{"height":150,"width":150,"url":"https:\/\/bringatrailer.com\/wp-content\/uploads\/2024\/03\/1969_mg_mgc-roadster_mgc-8-55211.jpg?resize=235%2C159"},"large":{"height":150,"width":150,"url":"https:\/\/bringatrailer.com\/wp-content\/uploads\/2024\/03\/1969_mg_mgc-roadster_mgc-8-55211.jpg?resize=235%2C159"}}},{"id":72528693,"url":"https:\/\/bringatrailer.com\/listing\/lunch-with-gm-president\/","title":"Experience for Charity: Lunch with GM President Mark Reuss","subtitle":"Sold for $36,000  on 4\/9\/24 ","images":{"small":{"height":150,"width":150,"url":"https:\/\/bringatrailer.com\/wp-content\/uploads\/2024\/03\/MLR-headshot-50458-scaled.jpg?resize=235%2C159"},"large":{"height":150,"width":150,"url":"https:\/\/bringatrailer.com\/wp-content\/uploads\/2024\/03\/MLR-headshot-50458-scaled.jpg?resize=235%2C159"}}},{"id":73627657,"url":"https:\/\/bringatrailer.com\/listing\/2010-ferrari-612-scaglietti-oto-3\/","title":"11k-Mile 2010 Ferrari 612 Scaglietti OTO","subtitle":"Sold for $177,000  on 4\/9\/24 ","images":{"small":{"height":150,"width":150,"url":"https:\/\/bringatrailer.com\/wp-content\/uploads\/2024\/04\/2010_ferrari_612-scaglietti-oto_img_2875-00574.jpeg?resize=235%2C159"},"large":{"height":150,"width":150,"url":"https:\/\/bringatrailer.com\/wp-content\/uploads\/2024\/04\/2010_ferrari_612-scaglietti-oto_img_2875-00574.jpeg?resize=235%2C159"}}},{"id":73278785,"url":"https:\/\/bringatrailer.com\/listing\/1968-mercury-cougar-29\/","title":"1968 Mercury Cougar Hardtop","subtitle":"Sold for $17,500  on 4\/9\/24 ","images":{"small":{"height":150,"width":150,"url":"https:\/\/bringatrailer.com\/wp-content\/uploads\/2024\/03\/1968_mercury_cougar_1968_mercury_cougar_0e67f5a8-60d4-477a-87f5-920809ae294d-pjwhbz-95474-95475-scaled.jpg?resize=235%2C159"},"large":{"height":150,"width":150,"url":"https:\/\/bringatrailer.com\/wp-content\/uploads\/2024\/03\/1968_mercury_cougar_1968_mercury_cougar_0e67f5a8-60d4-477a-87f5-920809ae294d-pjwhbz-95474-95475-scaled.jpg?resize=235%2C159"}}},{"id":73450488,"url":"https:\/\/bringatrailer.com\/listing\/2012-fiat-500-abarth-2\/","title":"40k-Mile 2012 Fiat 500 Abarth","subtitle":"Sold for $17,000  on 4\/9\/24 ","images":{"small":{"height":150,"width":150,"url":"https:\/\/bringatrailer.com\/wp-content\/uploads\/2024\/03\/2012_fiat_500-abarth_dsc03041-28831.jpg?resize=235%2C159"},"large":{"height":150,"width":150,"url":"https:\/\/bringatrailer.com\/wp-content\/uploads\/2024\/03\/2012_fiat_500-abarth_dsc03041-28831.jpg?resize=235%2C159"}}},{"id":73402130,"url":"https:\/\/bringatrailer.com\/listing\/1968-porsche-911-35\/","title":"No Reserve: Flat-Four-Powered 1968 Porsche 911 Coupe Project","subtitle":"Sold for $26,150  on 4\/9\/24 ","images":{"small":{"height":150,"width":150,"url":"https:\/\/bringatrailer.com\/wp-content\/uploads\/2024\/03\/1968_porsche_911_1968-porsche-911-cpe-0014-51128.jpg?resize=235%2C159"},"large":{"height":150,"width":150,"url":"https:\/\/bringatrailer.com\/wp-content\/uploads\/2024\/03\/1968_porsche_911_1968-porsche-911-cpe-0014-51128.jpg?resize=235%2C159"}}},{"id":72866733,"url":"https:\/\/bringatrailer.com\/listing\/1976-datsun-280z-86\/","title":"1976 Datsun 280Z 5-Speed","subtitle":"Bid to $21,250  on 4\/9\/24 ","images":{"small":{"height":150,"width":150,"url":"https:\/\/bringatrailer.com\/wp-content\/uploads\/2024\/03\/1976_datsun_280z_p1077797edit2-77557.jpg?resize=235%2C159"},"large":{"height":150,"width":150,"url":"https:\/\/bringatrailer.com\/wp-content\/uploads\/2024\/03\/1976_datsun_280z_p1077797edit2-77557.jpg?resize=235%2C159"}}},{"id":72233209,"url":"https:\/\/bringatrailer.com\/listing\/2018-bmw-m3-cs-35\/","title":"9k-Kilometer 2018 BMW M3 CS","subtitle":"Bid to $56,850  on 4\/9\/24 ","images":{"small":{"height":150,"width":150,"url":"https:\/\/bringatrailer.com\/wp-content\/uploads\/2024\/03\/2018_bmw_m3-cs_2018_bmw_m3-cs_395df4c7-9f72-47eb-9348-c40f080e0033-hoFCWX-56588-56588-scaled.jpg?resize=235%2C159"},"large":{"height":150,"width":150,"url":"https:\/\/bringatrailer.com\/wp-content\/uploads\/2024\/03\/2018_bmw_m3-cs_2018_bmw_m3-cs_395df4c7-9f72-47eb-9348-c40f080e0033-hoFCWX-56588-56588-scaled.jpg?resize=235%2C159"}}},{"id":70181046,"url":"https:\/\/bringatrailer.com\/listing\/1961-alfa-romeo-giulietta-berlina-1300-ti-2\/","title":"1961 Alfa Romeo Giulietta TI","subtitle":"Sold for $24,000  on 4\/9\/24 ","images":{"small":{"height":150,"width":150,"url":"https:\/\/bringatrailer.com\/wp-content\/uploads\/2024\/01\/1961_alfa-romeo_giulietta-berlina-1300-ti_1961_alfa-romeo_giulietta-berlina-1300-ti_1524acad-f75d-404b-8695-98d5114a7cbb-0asfw3-86505-45893.jpg?resize=235%2C159"},"large":{"height":150,"width":150,"url":"https:\/\/bringatrailer.com\/wp-content\/uploads\/2024\/01\/1961_alfa-romeo_giulietta-berlina-1300-ti_1961_alfa-romeo_giulietta-berlina-1300-ti_1524acad-f75d-404b-8695-98d5114a7cbb-0asfw3-86505-45893.jpg?resize=235%2C159"}}},{"id":73389068,"url":"https:\/\/bringatrailer.com\/listing\/2023-chevrolet-corvette-z06-convertible-112-2\/","title":"2023 Chevrolet Corvette Z06 Convertible 3LZ Z07","subtitle":"Bid to $171,000  on 4\/9\/24 ","images":{"small":{"height":150,"width":150,"url":"https:\/\/bringatrailer.com\/wp-content\/uploads\/2024\/03\/2023_chevrolet_corvette-z06-convertible_img_9950-68735.jpeg?resize=235%2C159"},"large":{"height":150,"width":150,"url":"https:\/\/bringatrailer.com\/wp-content\/uploads\/2024\/03\/2023_chevrolet_corvette-z06-convertible_img_9950-68735.jpeg?resize=235%2C159"}}},{"id":73237372,"url":"https:\/\/bringatrailer.com\/listing\/2013-mercedes-benz-sl65-amg-6\/","title":"30k-Mile 2013 Mercedes-Benz SL65 AMG","subtitle":"Sold for $78,000  on 4\/9\/24 ","images":{"small":{"height":150,"width":150,"url":"https:\/\/bringatrailer.com\/wp-content\/uploads\/2024\/03\/2013_mercedes-benz_sl65-amg_2013_mercedes-benz_sl65-amg_27d3715e-0361-4efb-b831-266c62a61d96-r0y7zd-88317-86193.jpg?resize=235%2C159"},"large":{"height":150,"width":150,"url":"https:\/\/bringatrailer.com\/wp-content\/uploads\/2024\/03\/2013_mercedes-benz_sl65-amg_2013_mercedes-benz_sl65-amg_27d3715e-0361-4efb-b831-266c62a61d96-r0y7zd-88317-86193.jpg?resize=235%2C159"}}},{"id":72424046,"url":"https:\/\/bringatrailer.com\/listing\/1982-toyota-land-cruiser-bj46\/","title":"1982 Toyota Land Cruiser BJ46","subtitle":"Sold for $21,000  on 4\/9\/24 ","images":{"small":{"height":150,"width":150,"url":"https:\/\/bringatrailer.com\/wp-content\/uploads\/2024\/03\/1982_toyota_land-cruiser-bj46_sst-24-09-01-56988.jpg?resize=235%2C159"},"large":{"height":150,"width":150,"url":"https:\/\/bringatrailer.com\/wp-content\/uploads\/2024\/03\/1982_toyota_land-cruiser-bj46_sst-24-09-01-56988.jpg?resize=235%2C159"}}},{"id":73269604,"url":"https:\/\/bringatrailer.com\/listing\/1974-volkswagen-bus-t1-split-window-3\/","title":"1974 Volkswagen Type 2 23-Window Conversion","subtitle":"Sold for $35,500  on 4\/9\/24 ","images":{"small":{"height":150,"width":150,"url":"https:\/\/bringatrailer.com\/wp-content\/uploads\/2024\/03\/1974_volkswagen_bus-t1-split-window_bus-070-07718.jpg?resize=235%2C159"},"large":{"height":150,"width":150,"url":"https:\/\/bringatrailer.com\/wp-content\/uploads\/2024\/03\/1974_volkswagen_bus-t1-split-window_bus-070-07718.jpg?resize=235%2C159"}}},{"id":73574362,"url":"https:\/\/bringatrailer.com\/listing\/1993-ford-probe-7\/","title":"No Reserve: 7k-Mile 1993 Ford Probe GT","subtitle":"Sold for $18,000  on 4\/9\/24 ","images":{"small":{"height":150,"width":150,"url":"https:\/\/bringatrailer.com\/wp-content\/uploads\/2024\/03\/1993_ford_probe_img_9546-88820.jpg?resize=235%2C159"},"large":{"height":150,"width":150,"url":"https:\/\/bringatrailer.com\/wp-content\/uploads\/2024\/03\/1993_ford_probe_img_9546-88820.jpg?resize=235%2C159"}}},{"id":73287627,"url":"https:\/\/bringatrailer.com\/listing\/1991-porsche-911-carrera-2-cabriolet-22\/","title":"1991 Porsche 911 Carrera 2 Cabriolet 5-Speed","subtitle":"Sold for $51,500  on 4\/9\/24 ","images":{"small":{"height":150,"width":150,"url":"https:\/\/bringatrailer.com\/wp-content\/uploads\/2024\/03\/1991_porsche_911-carrera-2-cabriolet_nb9a0499-73082.jpg?resize=235%2C159"},"large":{"height":150,"width":150,"url":"https:\/\/bringatrailer.com\/wp-content\/uploads\/2024\/03\/1991_porsche_911-carrera-2-cabriolet_nb9a0499-73082.jpg?resize=235%2C159"}}},{"id":73333889,"url":"https:\/\/bringatrailer.com\/listing\/2002-porsche-911-carrera-4s-coupe-19\/","title":"No Reserve: RWD-Converted 2002 Porsche 911 Carrera 4S Coupe 6-Speed","subtitle":"Sold for $17,250  on 4\/9\/24 ","images":{"small":{"height":150,"width":150,"url":"https:\/\/bringatrailer.com\/wp-content\/uploads\/2024\/03\/2002_porsche_911-carrera-4s-coupe_img_6675-56507.jpeg?resize=235%2C159"},"large":{"height":150,"width":150,"url":"https:\/\/bringatrailer.com\/wp-content\/uploads\/2024\/03\/2002_porsche_911-carrera-4s-coupe_img_6675-56507.jpeg?resize=235%2C159"}}},{"id":73047982,"url":"https:\/\/bringatrailer.com\/listing\/2020-porsche-911-carrera-4s-cabriolet-7\/","title":"2020 Porsche 911 Carrera 4S Cabriolet","subtitle":"Sold for $112,000  on 4\/9\/24 ","images":{"small":{"height":150,"width":150,"url":"https:\/\/bringatrailer.com\/wp-content\/uploads\/2024\/03\/2020_porsche_911-carrera-4s-cabriolet_2020_porsche_911-carrera-4s-cabriolet_41e29337-b973-4df0-a93a-f67ebc58b584-yptxwn-80883-78622.jpg?resize=235%2C159"},"large":{"height":150,"width":150,"url":"https:\/\/bringatrailer.com\/wp-content\/uploads\/2024\/03\/2020_porsche_911-carrera-4s-cabriolet_2020_porsche_911-carrera-4s-cabriolet_41e29337-b973-4df0-a93a-f67ebc58b584-yptxwn-80883-78622.jpg?resize=235%2C159"}}},{"id":73180971,"url":"https:\/\/bringatrailer.com\/listing\/2002-bmw-330i-sedan-4\/","title":"2002 BMW 330i Sedan Sport","subtitle":"Sold for $16,500  on 4\/9\/24 ","images":{"small":{"height":150,"width":150,"url":"https:\/\/bringatrailer.com\/wp-content\/uploads\/2024\/03\/2002_bmw_330i-sedan_img_2913-68060.jpg?resize=235%2C159"},"large":{"height":150,"width":150,"url":"https:\/\/bringatrailer.com\/wp-content\/uploads\/2024\/03\/2002_bmw_330i-sedan_img_2913-68060.jpg?resize=235%2C159"}}},{"id":73285084,"url":"https:\/\/bringatrailer.com\/listing\/2014-land-rover-lr4-14\/","title":"No Reserve: 34k-Mile 2014 Land Rover LR4 HSE","subtitle":"Sold for $32,000  on 4\/9\/24 ","images":{"small":{"height":150,"width":150,"url":"https:\/\/bringatrailer.com\/wp-content\/uploads\/2024\/03\/2014_land-rover_lr4_mg_3843-64722.jpg?resize=235%2C159"},"large":{"height":150,"width":150,"url":"https:\/\/bringatrailer.com\/wp-content\/uploads\/2024\/03\/2014_land-rover_lr4_mg_3843-64722.jpg?resize=235%2C159"}}},{"id":73036006,"url":"https:\/\/bringatrailer.com\/listing\/1961-cadillac-series-62-2\/","title":"1961 Cadillac Series 62 Coupe","subtitle":"Bid to $23,850  on 4\/9\/24 ","images":{"small":{"height":150,"width":150,"url":"https:\/\/bringatrailer.com\/wp-content\/uploads\/2024\/03\/1961_cadillac_series-62_1961-cadillac-series-62-labanieh-photography-004-dsc05904-52285.jpg?resize=235%2C159"},"large":{"height":150,"width":150,"url":"https:\/\/bringatrailer.com\/wp-content\/uploads\/2024\/03\/1961_cadillac_series-62_1961-cadillac-series-62-labanieh-photography-004-dsc05904-52285.jpg?resize=235%2C159"}}},{"id":73539824,"url":"https:\/\/bringatrailer.com\/listing\/2018-porsche-911-gt2-rs-41\/","title":"2018 Porsche 911 GT2 RS Weissach","subtitle":"Sold for $303,000  on 4\/9\/24 ","images":{"small":{"height":150,"width":150,"url":"https:\/\/bringatrailer.com\/wp-content\/uploads\/2024\/03\/Web-50205-18-Porsche-GT2RS-1-68348.jpg?resize=235%2C159"},"large":{"height":150,"width":150,"url":"https:\/\/bringatrailer.com\/wp-content\/uploads\/2024\/03\/Web-50205-18-Porsche-GT2RS-1-68348.jpg?resize=235%2C159"}}},{"id":73211097,"url":"https:\/\/bringatrailer.com\/listing\/1974-honda-cb750-42\/","title":"No Reserve: 1974 Honda CB750","subtitle":"Sold for $8,000  on 4\/9\/24 ","images":{"small":{"height":150,"width":150,"url":"https:\/\/bringatrailer.com\/wp-content\/uploads\/2024\/03\/1974_honda_cb750_img_2748-15798.jpeg?resize=235%2C159"},"large":{"height":150,"width":150,"url":"https:\/\/bringatrailer.com\/wp-content\/uploads\/2024\/03\/1974_honda_cb750_img_2748-15798.jpeg?resize=235%2C159"}}},{"id":72974622,"url":"https:\/\/bringatrailer.com\/listing\/2004-bmw-m3-coupe-182\/","title":"2004 BMW M3 Coupe 6-Speed","subtitle":"Sold for $63,300  on 4\/9\/24 ","images":{"small":{"height":150,"width":150,"url":"https:\/\/bringatrailer.com\/wp-content\/uploads\/2024\/03\/2004_bmw_m3-coupe_Web-E46-M3-Ext-1-80169.jpg?resize=235%2C159"},"large":{"height":150,"width":150,"url":"https:\/\/bringatrailer.com\/wp-content\/uploads\/2024\/03\/2004_bmw_m3-coupe_Web-E46-M3-Ext-1-80169.jpg?resize=235%2C159"}}},{"id":72806504,"url":"https:\/\/bringatrailer.com\/listing\/1994-porsche-968-coupe-22\/","title":"1994 Porsche 968 Coupe 6-Speed","subtitle":"Sold for $19,600  on 4\/9\/24 ","images":{"small":{"height":150,"width":150,"url":"https:\/\/bringatrailer.com\/wp-content\/uploads\/2024\/03\/1994_porsche_968-coupe_1994_porsche_968-coupe_53f64a6c-fed5-4c4f-b2c7-86ec0c86b7d4-e6XcN9-22020-22021-scaled.jpg?resize=235%2C159"},"large":{"height":150,"width":150,"url":"https:\/\/bringatrailer.com\/wp-content\/uploads\/2024\/03\/1994_porsche_968-coupe_1994_porsche_968-coupe_53f64a6c-fed5-4c4f-b2c7-86ec0c86b7d4-e6XcN9-22020-22021-scaled.jpg?resize=235%2C159"}}},{"id":73167318,"url":"https:\/\/bringatrailer.com\/listing\/2024-chevrolet-camaro-coupe-16\/","title":"2024 Chevrolet Camaro Coupe ZL1 Collector Edition 6-Speed","subtitle":"Bid to $125,000  on 4\/9\/24 ","images":{"small":{"height":150,"width":150,"url":"https:\/\/bringatrailer.com\/wp-content\/uploads\/2024\/03\/2024_chevrolet_camaro-coupe_img_3120-46937.jpg?resize=235%2C159"},"large":{"height":150,"width":150,"url":"https:\/\/bringatrailer.com\/wp-content\/uploads\/2024\/03\/2024_chevrolet_camaro-coupe_img_3120-46937.jpg?resize=235%2C159"}}},{"id":72932330,"url":"https:\/\/bringatrailer.com\/listing\/2018-porsche-911-gt3-104\/","title":"2018 Porsche 911 GT3","subtitle":"Bid to $177,500  on 4\/9\/24 ","images":{"small":{"height":150,"width":150,"url":"https:\/\/bringatrailer.com\/wp-content\/uploads\/2024\/03\/2018_porsche_911-gt3_2018_porsche_911-gt3_643c6596-6794-46d2-9f58-a3268059379f-tXIxTP-21694-21695-scaled.jpg?resize=235%2C159"},"large":{"height":150,"width":150,"url":"https:\/\/bringatrailer.com\/wp-content\/uploads\/2024\/03\/2018_porsche_911-gt3_2018_porsche_911-gt3_643c6596-6794-46d2-9f58-a3268059379f-tXIxTP-21694-21695-scaled.jpg?resize=235%2C159"}}},{"id":72714517,"url":"https:\/\/bringatrailer.com\/listing\/1960-daimler-sp250-3\/","title":"1960 Daimler SP250","subtitle":"Bid to $16,925  on 4\/9\/24 ","images":{"small":{"height":150,"width":150,"url":"https:\/\/bringatrailer.com\/wp-content\/uploads\/2024\/03\/1960_daimler_sp250_img_2089-28140.jpeg?resize=235%2C159"},"large":{"height":150,"width":150,"url":"https:\/\/bringatrailer.com\/wp-content\/uploads\/2024\/03\/1960_daimler_sp250_img_2089-28140.jpeg?resize=235%2C159"}}},{"id":72225560,"url":"https:\/\/bringatrailer.com\/listing\/1995-polaris-xlt-special\/","title":"No Reserve: 1995 Polaris Indy XLT Special 600","subtitle":"Sold for $7,600  on 4\/9\/24 ","images":{"small":{"height":150,"width":150,"url":"https:\/\/bringatrailer.com\/wp-content\/uploads\/2024\/03\/1995_polaris_xlt-special_polaris-snowmobile-daylight-2024-03-21-0002-61030.jpg?resize=235%2C159"},"large":{"height":150,"width":150,"url":"https:\/\/bringatrailer.com\/wp-content\/uploads\/2024\/03\/1995_polaris_xlt-special_polaris-snowmobile-daylight-2024-03-21-0002-61030.jpg?resize=235%2C159"}}},{"id":71071185,"url":"https:\/\/bringatrailer.com\/listing\/1969-alfa-romeo-gtv-1750-15\/","title":"1969 Alfa Romeo GTV 1750","subtitle":"Sold for $61,500  on 4\/9\/24 ","images":{"small":{"height":150,"width":150,"url":"https:\/\/bringatrailer.com\/wp-content\/uploads\/2024\/02\/1969_alfa-romeo_gtv-1750_080-37036-scaled.jpg?resize=235%2C159"},"large":{"height":150,"width":150,"url":"https:\/\/bringatrailer.com\/wp-content\/uploads\/2024\/02\/1969_alfa-romeo_gtv-1750_080-37036-scaled.jpg?resize=235%2C159"}}},{"id":73476287,"url":"https:\/\/bringatrailer.com\/listing\/2017-porsche-cayenne-10\/","title":"2017 Porsche Cayenne Platinum Edition","subtitle":"Sold for $28,006  on 4\/9\/24 ","images":{"small":{"height":150,"width":150,"url":"https:\/\/bringatrailer.com\/wp-content\/uploads\/2024\/03\/2017_porsche_cayenne_img_20240326_124029714-98237.jpg?resize=235%2C159"},"large":{"height":150,"width":150,"url":"https:\/\/bringatrailer.com\/wp-content\/uploads\/2024\/03\/2017_porsche_cayenne_img_20240326_124029714-98237.jpg?resize=235%2C159"}}},{"id":72886482,"url":"https:\/\/bringatrailer.com\/listing\/meyers-manx-31\/","title":"Meyers Manx Kick-Out","subtitle":"Sold for $30,500  on 4\/9\/24 ","images":{"small":{"height":150,"width":150,"url":"https:\/\/bringatrailer.com\/wp-content\/uploads\/2024\/03\/1973_meyers_manx_1973_meyers_manx_3fe0244f-4480-4e3b-aa66-e59065c280d0-C82gEJ-15207-15207-scaled.jpg?resize=235%2C159"},"large":{"height":150,"width":150,"url":"https:\/\/bringatrailer.com\/wp-content\/uploads\/2024\/03\/1973_meyers_manx_1973_meyers_manx_3fe0244f-4480-4e3b-aa66-e59065c280d0-C82gEJ-15207-15207-scaled.jpg?resize=235%2C159"}}}]}