{"page_current":1,"page_maximum":6741,"total":215702,"items":[{"id":102125775,"url":"https:\/\/bringatrailer.com\/listing\/1990-ferrari-testarossa-63\/","title":"1990 Ferrari Testarossa","subtitle":"Sold for USD $155,500  on 10\/19\/25 ","images":{"small":{"height":150,"width":150,"url":"https:\/\/bringatrailer.com\/wp-content\/uploads\/2025\/09\/1990_ferrari_testarossa_img_0936-77613.jpeg?resize=235%2C159"},"large":{"height":150,"width":150,"url":"https:\/\/bringatrailer.com\/wp-content\/uploads\/2025\/09\/1990_ferrari_testarossa_img_0936-77613.jpeg?resize=235%2C159"}}},{"id":102962044,"url":"https:\/\/bringatrailer.com\/listing\/2001-ford-excursion-155\/","title":"No Reserve: 2001 Ford Excursion Limited Power Stroke 4\u00d74","subtitle":"Sold for USD $28,500  on 10\/19\/25 ","images":{"small":{"height":150,"width":150,"url":"https:\/\/bringatrailer.com\/wp-content\/uploads\/2025\/10\/2001_ford_excursion_dsc_1684-59360.jpg?resize=235%2C159"},"large":{"height":150,"width":150,"url":"https:\/\/bringatrailer.com\/wp-content\/uploads\/2025\/10\/2001_ford_excursion_dsc_1684-59360.jpg?resize=235%2C159"}}},{"id":102133249,"url":"https:\/\/bringatrailer.com\/listing\/2010-ferrari-458-italia-35\/","title":"No Reserve: 2010 Ferrari 458 Italia","subtitle":"Sold for USD $162,650  on 10\/19\/25 ","images":{"small":{"height":150,"width":150,"url":"https:\/\/bringatrailer.com\/wp-content\/uploads\/2025\/09\/2010_ferrari_458-italia_2010_ferrari_458-italia_c667c824-5c5b-4819-936f-79883d25a8bf-pmxlbi-97466-35358.jpg?resize=235%2C159"},"large":{"height":150,"width":150,"url":"https:\/\/bringatrailer.com\/wp-content\/uploads\/2025\/09\/2010_ferrari_458-italia_2010_ferrari_458-italia_c667c824-5c5b-4819-936f-79883d25a8bf-pmxlbi-97466-35358.jpg?resize=235%2C159"}}},{"id":94892811,"url":"https:\/\/bringatrailer.com\/listing\/2004-honda-vtr1000-rc51\/","title":"2004 Honda RVT1000R RC51 Nicky Hayden Edition","subtitle":"Sold for USD $31,051  on 10\/19\/25 ","images":{"small":{"height":150,"width":150,"url":"https:\/\/bringatrailer.com\/wp-content\/uploads\/2025\/05\/2004_honda_vtr1000r-rc51_2004-Honda_RVT100R-010-59684-scaled.jpg?resize=235%2C159"},"large":{"height":150,"width":150,"url":"https:\/\/bringatrailer.com\/wp-content\/uploads\/2025\/05\/2004_honda_vtr1000r-rc51_2004-Honda_RVT100R-010-59684-scaled.jpg?resize=235%2C159"}}},{"id":102061014,"url":"https:\/\/bringatrailer.com\/listing\/2016-mercedes-amg-g63-32\/","title":"2016 Mercedes-AMG G63","subtitle":"Bid to USD $61,000  on 10\/19\/25 ","images":{"small":{"height":150,"width":150,"url":"https:\/\/bringatrailer.com\/wp-content\/uploads\/2025\/09\/2016_mercedes-amg_g63_img_1400-jpeg-16962.jpg?resize=235%2C159"},"large":{"height":150,"width":150,"url":"https:\/\/bringatrailer.com\/wp-content\/uploads\/2025\/09\/2016_mercedes-amg_g63_img_1400-jpeg-16962.jpg?resize=235%2C159"}}},{"id":102382987,"url":"https:\/\/bringatrailer.com\/listing\/2013-porsche-cayenne-gts-71\/","title":"No Reserve: 2013 Porsche Cayenne GTS","subtitle":"Sold for USD $20,000  on 10\/19\/25 ","images":{"small":{"height":150,"width":150,"url":"https:\/\/bringatrailer.com\/wp-content\/uploads\/2025\/09\/2013_porsche_cayenne-gts_img_3506-70353.jpg?resize=235%2C159"},"large":{"height":150,"width":150,"url":"https:\/\/bringatrailer.com\/wp-content\/uploads\/2025\/09\/2013_porsche_cayenne-gts_img_3506-70353.jpg?resize=235%2C159"}}},{"id":102738892,"url":"https:\/\/bringatrailer.com\/listing\/2000-mercedes-benz-sl500-184\/","title":"2000 Mercedes-Benz SL500","subtitle":"Sold for USD $10,000  on 10\/19\/25 ","images":{"small":{"height":150,"width":150,"url":"https:\/\/bringatrailer.com\/wp-content\/uploads\/2025\/09\/2000_mercedes-benz_sl500_img_8180-86359.jpeg?resize=235%2C159"},"large":{"height":150,"width":150,"url":"https:\/\/bringatrailer.com\/wp-content\/uploads\/2025\/09\/2000_mercedes-benz_sl500_img_8180-86359.jpeg?resize=235%2C159"}}},{"id":100550645,"url":"https:\/\/bringatrailer.com\/listing\/2003-ferrari-575m-maranello-21\/","title":"2003 Ferrari 575M Maranello","subtitle":"Sold for USD $90,000  on 10\/19\/25 ","images":{"small":{"height":150,"width":150,"url":"https:\/\/bringatrailer.com\/wp-content\/uploads\/2025\/08\/2003_ferrari_575m-maranello_314af715-43f5-447a-958e-aa00474b9389-19728.jpeg?resize=235%2C159"},"large":{"height":150,"width":150,"url":"https:\/\/bringatrailer.com\/wp-content\/uploads\/2025\/08\/2003_ferrari_575m-maranello_314af715-43f5-447a-958e-aa00474b9389-19728.jpeg?resize=235%2C159"}}},{"id":98976368,"url":"https:\/\/bringatrailer.com\/listing\/2004-ford-thunderbird-126\/","title":"No Reserve: 2004 Ford Thunderbird","subtitle":"Sold for USD $10,250  on 10\/19\/25 ","images":{"small":{"height":150,"width":150,"url":"https:\/\/bringatrailer.com\/wp-content\/uploads\/2025\/07\/2004_ford_thunderbird_tbird-17-29828.jpeg?resize=235%2C159"},"large":{"height":150,"width":150,"url":"https:\/\/bringatrailer.com\/wp-content\/uploads\/2025\/07\/2004_ford_thunderbird_tbird-17-29828.jpeg?resize=235%2C159"}}},{"id":102146255,"url":"https:\/\/bringatrailer.com\/listing\/scale-model-47\/","title":"No Reserve: Half-Scale McLaren MCL Display Model","subtitle":"Sold for USD $11,300  on 10\/19\/25 ","images":{"small":{"height":150,"width":150,"url":"https:\/\/bringatrailer.com\/wp-content\/uploads\/2025\/09\/dsc02601-23860.jpg?resize=235%2C159"},"large":{"height":150,"width":150,"url":"https:\/\/bringatrailer.com\/wp-content\/uploads\/2025\/09\/dsc02601-23860.jpg?resize=235%2C159"}}},{"id":101429424,"url":"https:\/\/bringatrailer.com\/listing\/1965-mercedes-benz-230sl-73\/","title":"42-Years-Owned 1965 Mercedes-Benz 230SL 4-Speed","subtitle":"Sold for USD $30,250  on 10\/19\/25 ","images":{"small":{"height":150,"width":150,"url":"https:\/\/bringatrailer.com\/wp-content\/uploads\/2025\/09\/1965_mercedes-benz_230sl_1965_mercedes-benz_230sl_204f0fc1-3d8f-428f-b52a-2f0f13904d0f-zflui3-80836-03590.jpg?resize=235%2C159"},"large":{"height":150,"width":150,"url":"https:\/\/bringatrailer.com\/wp-content\/uploads\/2025\/09\/1965_mercedes-benz_230sl_1965_mercedes-benz_230sl_204f0fc1-3d8f-428f-b52a-2f0f13904d0f-zflui3-80836-03590.jpg?resize=235%2C159"}}},{"id":103152603,"url":"https:\/\/bringatrailer.com\/listing\/1996-cadillac-fleetwood-brougham-5\/","title":"47k-Mile 1996 Cadillac Fleetwood Brougham","subtitle":"Sold for USD $10,400  on 10\/19\/25 ","images":{"small":{"height":150,"width":150,"url":"https:\/\/bringatrailer.com\/wp-content\/uploads\/2025\/10\/1996_cadillac_fleetwood-brougham_dsc00927-33826.jpg?resize=235%2C159"},"large":{"height":150,"width":150,"url":"https:\/\/bringatrailer.com\/wp-content\/uploads\/2025\/10\/1996_cadillac_fleetwood-brougham_dsc00927-33826.jpg?resize=235%2C159"}}},{"id":101898784,"url":"https:\/\/bringatrailer.com\/listing\/2011-porsche-911-carrera-s-cabriolet-14\/","title":"2011 Porsche 911 Carrera S Cabriolet 6-Speed","subtitle":"Sold for USD $44,000  on 10\/19\/25 ","images":{"small":{"height":150,"width":150,"url":"https:\/\/bringatrailer.com\/wp-content\/uploads\/2025\/09\/2011_porsche_911-carrera-s-cabriolet_Untitled-38895-46053-scaled.jpg?resize=235%2C159"},"large":{"height":150,"width":150,"url":"https:\/\/bringatrailer.com\/wp-content\/uploads\/2025\/09\/2011_porsche_911-carrera-s-cabriolet_Untitled-38895-46053-scaled.jpg?resize=235%2C159"}}},{"id":100030398,"url":"https:\/\/bringatrailer.com\/listing\/1972-bmw-2002-106\/","title":"No Reserve: One-Owner 1972 BMW 2002 4-Speed","subtitle":"Sold for USD $21,000  on 10\/19\/25 ","images":{"small":{"height":150,"width":150,"url":"https:\/\/bringatrailer.com\/wp-content\/uploads\/2025\/08\/1972_bmw_2002_img_1779-32431.jpg?resize=235%2C159"},"large":{"height":150,"width":150,"url":"https:\/\/bringatrailer.com\/wp-content\/uploads\/2025\/08\/1972_bmw_2002_img_1779-32431.jpg?resize=235%2C159"}}},{"id":102320542,"url":"https:\/\/bringatrailer.com\/listing\/1998-jeep-wrangler-70\/","title":"No Reserve: 1998 Jeep Wrangler SE","subtitle":"Sold for USD $5,600  on 10\/19\/25 ","images":{"small":{"height":150,"width":150,"url":"https:\/\/bringatrailer.com\/wp-content\/uploads\/2025\/09\/1998_jeep_wrangler_1-01223.jpg?resize=235%2C159"},"large":{"height":150,"width":150,"url":"https:\/\/bringatrailer.com\/wp-content\/uploads\/2025\/09\/1998_jeep_wrangler_1-01223.jpg?resize=235%2C159"}}},{"id":80455202,"url":"https:\/\/bringatrailer.com\/listing\/2005-chevrolet-ssr-113\/","title":"No Reserve: 24k-Mile 2005 Chevrolet SSR 6-Speed","subtitle":"Sold for USD $24,850  on 10\/19\/25 ","images":{"small":{"height":150,"width":150,"url":"https:\/\/bringatrailer.com\/wp-content\/uploads\/2024\/08\/2005_chevrolet_ssr_img_1853-41525.jpeg?resize=235%2C159"},"large":{"height":150,"width":150,"url":"https:\/\/bringatrailer.com\/wp-content\/uploads\/2024\/08\/2005_chevrolet_ssr_img_1853-41525.jpeg?resize=235%2C159"}}},{"id":103115409,"url":"https:\/\/bringatrailer.com\/listing\/1995-ducati-916-24\/","title":"No Reserve: 27-Years-Owned, Modified 1995 Ducati 916","subtitle":"Sold for USD $10,750  on 10\/19\/25 ","images":{"small":{"height":150,"width":150,"url":"https:\/\/bringatrailer.com\/wp-content\/uploads\/2025\/10\/1995_ducati_916_20250930_055625-44634.jpg?resize=235%2C159"},"large":{"height":150,"width":150,"url":"https:\/\/bringatrailer.com\/wp-content\/uploads\/2025\/10\/1995_ducati_916_20250930_055625-44634.jpg?resize=235%2C159"}}},{"id":100507683,"url":"https:\/\/bringatrailer.com\/listing\/2010-toyota-fj-cruiser-70\/","title":"No Reserve: 2010 Toyota FJ Cruiser 6-Speed","subtitle":"Sold for USD $38,999  on 10\/19\/25 ","images":{"small":{"height":150,"width":150,"url":"https:\/\/bringatrailer.com\/wp-content\/uploads\/2025\/08\/2010_toyota_fj-cruiser_2010_toyota_fj-cruiser_5afd0556-dbab-46e2-ae1c-ac4104aac722-py9fe5-26075-87698.jpg?resize=235%2C159"},"large":{"height":150,"width":150,"url":"https:\/\/bringatrailer.com\/wp-content\/uploads\/2025\/08\/2010_toyota_fj-cruiser_2010_toyota_fj-cruiser_5afd0556-dbab-46e2-ae1c-ac4104aac722-py9fe5-26075-87698.jpg?resize=235%2C159"}}},{"id":102292983,"url":"https:\/\/bringatrailer.com\/listing\/2024-jeep-wrangler-rubicon-392-4\/","title":"448 Stroker-Powered 2024 Jeep Wrangler Rubicon 392 Four-Door","subtitle":"Sold for USD $84,500  on 10\/19\/25 ","images":{"small":{"height":150,"width":150,"url":"https:\/\/bringatrailer.com\/wp-content\/uploads\/2025\/09\/2024_jeep_wrangler-all-trims_2024_jeep_wrangler-all-trims_d86c4006-96d3-4a21-9fbb-8e4aaa96392b-cgivye-81124-83123.jpg?resize=235%2C159"},"large":{"height":150,"width":150,"url":"https:\/\/bringatrailer.com\/wp-content\/uploads\/2025\/09\/2024_jeep_wrangler-all-trims_2024_jeep_wrangler-all-trims_d86c4006-96d3-4a21-9fbb-8e4aaa96392b-cgivye-81124-83123.jpg?resize=235%2C159"}}},{"id":99847522,"url":"https:\/\/bringatrailer.com\/listing\/1989-porsche-911-turbo-cabriolet-48\/","title":"20-Years-Owned 1989 Porsche 911 Turbo Cabriolet","subtitle":"Sold for USD $130,500  on 10\/19\/25 ","images":{"small":{"height":150,"width":150,"url":"https:\/\/bringatrailer.com\/wp-content\/uploads\/2025\/08\/1989_porsche_911-turbo-cabriolet_exterior_13-63249.jpg?resize=235%2C159"},"large":{"height":150,"width":150,"url":"https:\/\/bringatrailer.com\/wp-content\/uploads\/2025\/08\/1989_porsche_911-turbo-cabriolet_exterior_13-63249.jpg?resize=235%2C159"}}},{"id":99458580,"url":"https:\/\/bringatrailer.com\/listing\/1996-porsche-911-carrera-coupe-87\/","title":"1996 Porsche 911 Carrera Coupe 6-Speed","subtitle":"Sold for USD $112,999  on 10\/19\/25 ","images":{"small":{"height":150,"width":150,"url":"https:\/\/bringatrailer.com\/wp-content\/uploads\/2025\/08\/1996_porsche_911-carrera-coupe_bat993-326-08436.jpg?resize=235%2C159"},"large":{"height":150,"width":150,"url":"https:\/\/bringatrailer.com\/wp-content\/uploads\/2025\/08\/1996_porsche_911-carrera-coupe_bat993-326-08436.jpg?resize=235%2C159"}}},{"id":101529316,"url":"https:\/\/bringatrailer.com\/listing\/1968-jaguar-xke-series-1-5-coupe-4-2\/","title":"1968 Jaguar XKE Series 1.5 4.2 Coupe","subtitle":"Bid to USD $65,500  on 10\/19\/25 ","images":{"small":{"height":150,"width":150,"url":"https:\/\/bringatrailer.com\/wp-content\/uploads\/2025\/09\/1968_jaguar_e-type-series-1.5-coupe_img_7351-15446.jpeg?resize=235%2C159"},"large":{"height":150,"width":150,"url":"https:\/\/bringatrailer.com\/wp-content\/uploads\/2025\/09\/1968_jaguar_e-type-series-1.5-coupe_img_7351-15446.jpeg?resize=235%2C159"}}},{"id":102817079,"url":"https:\/\/bringatrailer.com\/listing\/1965-nissan-patrol-3\/","title":"No Reserve: 1965 Nissan Patrol 4x4","subtitle":"Sold for USD $6,000  on 10\/19\/25 ","images":{"small":{"height":150,"width":150,"url":"https:\/\/bringatrailer.com\/wp-content\/uploads\/2025\/10\/1965_nissan_patrol_img_2117-57325.jpg?resize=235%2C159"},"large":{"height":150,"width":150,"url":"https:\/\/bringatrailer.com\/wp-content\/uploads\/2025\/10\/1965_nissan_patrol_img_2117-57325.jpg?resize=235%2C159"}}},{"id":102584061,"url":"https:\/\/bringatrailer.com\/listing\/2001-dodge-viper-rt-10-26\/","title":"33k-Mile 2001 Dodge Viper RT\/10","subtitle":"Sold for USD $56,000  on 10\/19\/25 ","images":{"small":{"height":150,"width":150,"url":"https:\/\/bringatrailer.com\/wp-content\/uploads\/2025\/09\/2001_dodge_viper-rt10_viper-87-37367.jpg?resize=235%2C159"},"large":{"height":150,"width":150,"url":"https:\/\/bringatrailer.com\/wp-content\/uploads\/2025\/09\/2001_dodge_viper-rt10_viper-87-37367.jpg?resize=235%2C159"}}},{"id":100531088,"url":"https:\/\/bringatrailer.com\/listing\/2006-scion-xb-6\/","title":"No Reserve: 42k-Mile 2006 Scion xB","subtitle":"Sold for USD $7,702  on 10\/19\/25 ","images":{"small":{"height":150,"width":150,"url":"https:\/\/bringatrailer.com\/wp-content\/uploads\/2025\/08\/2006_scion_xb_20250924_150255-85582.jpg?resize=235%2C159"},"large":{"height":150,"width":150,"url":"https:\/\/bringatrailer.com\/wp-content\/uploads\/2025\/08\/2006_scion_xb_20250924_150255-85582.jpg?resize=235%2C159"}}},{"id":102306301,"url":"https:\/\/bringatrailer.com\/listing\/1999-lexus-lx470-58\/","title":"1999 Lexus LX470","subtitle":"Sold for USD $19,000  on 10\/19\/25 ","images":{"small":{"height":150,"width":150,"url":"https:\/\/bringatrailer.com\/wp-content\/uploads\/2025\/09\/1999_lexus_lx470_img_7594-10996.jpeg?resize=235%2C159"},"large":{"height":150,"width":150,"url":"https:\/\/bringatrailer.com\/wp-content\/uploads\/2025\/09\/1999_lexus_lx470_img_7594-10996.jpeg?resize=235%2C159"}}},{"id":102720024,"url":"https:\/\/bringatrailer.com\/listing\/2019-mahindra-roxor-5\/","title":"No Reserve: 2019 Mahindra Roxor","subtitle":"Sold for USD $18,000  on 10\/19\/25 ","images":{"small":{"height":150,"width":150,"url":"https:\/\/bringatrailer.com\/wp-content\/uploads\/2025\/09\/2019_mahindra_mahindra-roxor_img_0953-67684.jpeg?resize=235%2C159"},"large":{"height":150,"width":150,"url":"https:\/\/bringatrailer.com\/wp-content\/uploads\/2025\/09\/2019_mahindra_mahindra-roxor_img_0953-67684.jpeg?resize=235%2C159"}}},{"id":102712263,"url":"https:\/\/bringatrailer.com\/listing\/2003-ford-ranger-26\/","title":"No Reserve: 43k-Mile 2003 Ford Ranger XLT 3.0L","subtitle":"Sold for USD $11,251  on 10\/19\/25 ","images":{"small":{"height":150,"width":150,"url":"https:\/\/bringatrailer.com\/wp-content\/uploads\/2025\/09\/2003_ford_ranger_img_2155-14149.jpeg?resize=235%2C159"},"large":{"height":150,"width":150,"url":"https:\/\/bringatrailer.com\/wp-content\/uploads\/2025\/09\/2003_ford_ranger_img_2155-14149.jpeg?resize=235%2C159"}}},{"id":103104727,"url":"https:\/\/bringatrailer.com\/listing\/1937-john-deere-model-b-long-frame-unstyled\/","title":"No Reserve: 1937 John Deere Model B","subtitle":"Sold for USD $11,300  on 10\/19\/25 ","images":{"small":{"height":150,"width":150,"url":"https:\/\/bringatrailer.com\/wp-content\/uploads\/2025\/10\/1937_john-deere_model-b-long-frame-unstyled_20251006_180856-20816.jpg?resize=235%2C159"},"large":{"height":150,"width":150,"url":"https:\/\/bringatrailer.com\/wp-content\/uploads\/2025\/10\/1937_john-deere_model-b-long-frame-unstyled_20251006_180856-20816.jpg?resize=235%2C159"}}},{"id":92098814,"url":"https:\/\/bringatrailer.com\/listing\/2005-bmw-x5-40\/","title":"No Reserve: 2005 BMW X5 4.8is","subtitle":"Sold for USD $8,500  on 10\/19\/25 ","images":{"small":{"height":150,"width":150,"url":"https:\/\/bringatrailer.com\/wp-content\/uploads\/2025\/04\/2005_bmw_x5_ADY8466-Enhanced-NR-78944-scaled.jpg?resize=235%2C159"},"large":{"height":150,"width":150,"url":"https:\/\/bringatrailer.com\/wp-content\/uploads\/2025\/04\/2005_bmw_x5_ADY8466-Enhanced-NR-78944-scaled.jpg?resize=235%2C159"}}},{"id":102694687,"url":"https:\/\/bringatrailer.com\/listing\/1968-ford-mustang-214-2\/","title":"No Reserve: GT350-Style 1968 Ford Mustang Convertible","subtitle":"Sold for USD $55,555  on 10\/19\/25 ","images":{"small":{"height":150,"width":150,"url":"https:\/\/bringatrailer.com\/wp-content\/uploads\/2025\/09\/1968_ford_mustang_p1100811-49707.jpg?resize=235%2C159"},"large":{"height":150,"width":150,"url":"https:\/\/bringatrailer.com\/wp-content\/uploads\/2025\/09\/1968_ford_mustang_p1100811-49707.jpg?resize=235%2C159"}}},{"id":102377936,"url":"https:\/\/bringatrailer.com\/listing\/1969-porsche-911t-coupe-14\/","title":"29-Years-Owned 1969 Porsche 911T Coupe Race Car 2.8L 5-Speed","subtitle":"Sold for USD $41,000  on 10\/19\/25 ","images":{"small":{"height":150,"width":150,"url":"https:\/\/bringatrailer.com\/wp-content\/uploads\/2025\/09\/1969_porsche_911t-coupe_1969_porsche_911t-coupe_2c46100d-e002-4aa4-88be-b49e51597f0a-T65nUG-57286-57287-scaled.jpg?resize=235%2C159"},"large":{"height":150,"width":150,"url":"https:\/\/bringatrailer.com\/wp-content\/uploads\/2025\/09\/1969_porsche_911t-coupe_1969_porsche_911t-coupe_2c46100d-e002-4aa4-88be-b49e51597f0a-T65nUG-57286-57287-scaled.jpg?resize=235%2C159"}}}]}